c3g_genpipes-6.1.0.dist-info/METADATA
c3g_genpipes-6.1.0.dist-info/WHEEL
c3g_genpipes-6.1.0.dist-info/entry_points.txt
c3g_genpipes-6.1.0.dist-info/licenses/COPYING
c3g_genpipes-6.1.0.dist-info/licenses/COPYING.LESSER
genpipes/__init__.py
genpipes/__main__.py
genpipes/__version__.py
genpipes/bfx/__init__.py
genpipes/bfx/adapters.py
genpipes/bfx/amber.py
genpipes/bfx/annoFuse.py
genpipes/bfx/annotations.py
genpipes/bfx/annotsv.py
genpipes/bfx/arriba.py
genpipes/bfx/artic.py
genpipes/bfx/ballgown.py
genpipes/bfx/bamreadcount.py
genpipes/bfx/bash_cmd.py
genpipes/bfx/bcbio_variation_recall.py
genpipes/bfx/bcftools.py
genpipes/bfx/bed_file.py
genpipes/bfx/bedops.py
genpipes/bfx/bedtools.py
genpipes/bfx/bigwiginfo.py
genpipes/bfx/bismark.py
genpipes/bfx/bissnp.py
genpipes/bfx/blast.py
genpipes/bfx/blat.py
genpipes/bfx/breakseq2.py
genpipes/bfx/bvatools.py
genpipes/bfx/bwa.py
genpipes/bfx/bwa2.py
genpipes/bfx/bwakit.py
genpipes/bfx/chicago.py
genpipes/bfx/chromimpute.py
genpipes/bfx/circlator.py
genpipes/bfx/clair3.py
genpipes/bfx/clairS.py
genpipes/bfx/cnvkit.py
genpipes/bfx/cobalt.py
genpipes/bfx/conpair.py
genpipes/bfx/covseq_tools.py
genpipes/bfx/cpsr.py
genpipes/bfx/cufflinks.py
genpipes/bfx/cutadapt.py
genpipes/bfx/dada2.py
genpipes/bfx/deeptools.py
genpipes/bfx/deepvariant.py
genpipes/bfx/deliverables.py
genpipes/bfx/delly.py
genpipes/bfx/differential_binding.py
genpipes/bfx/differential_expression.py
genpipes/bfx/discasm.py
genpipes/bfx/djerba.py
genpipes/bfx/dragen.py
genpipes/bfx/dysgu.py
genpipes/bfx/epigeec.py
genpipes/bfx/epiqc_reports.py
genpipes/bfx/exonerate.py
genpipes/bfx/fastp.py
genpipes/bfx/fastqc.py
genpipes/bfx/fgbio.py
genpipes/bfx/flash.py
genpipes/bfx/freebayes.py
genpipes/bfx/fusioninspector.py
genpipes/bfx/fusionmetacaller.py
genpipes/bfx/gatk.py
genpipes/bfx/gatk4.py
genpipes/bfx/gembs.py
genpipes/bfx/gemini.py
genpipes/bfx/genome.py
genpipes/bfx/gq_seq_utils.py
genpipes/bfx/gridss.py
genpipes/bfx/gripss.py
genpipes/bfx/gtex_pipeline.py
genpipes/bfx/guppy.py
genpipes/bfx/hic.py
genpipes/bfx/hicplotter.py
genpipes/bfx/hicrep.py
genpipes/bfx/hicup.py
genpipes/bfx/hificnv.py
genpipes/bfx/hiphase.py
genpipes/bfx/homer.py
genpipes/bfx/htseq.py
c3g_genpipes-6.1.0.dist-info/RECORD
