Metadata-Version: 2.1
Name: c3g-genpipes
Version: 6.1.0
Summary: Several bioinformatics pipelines developed at McGill University Genome Centre
Author-Email: Canadian Center for Computational Genomics <pipelines@computationalgenomics.ca>
Maintainer-Email: Mareike Janiak <mareike.janiak@computationalgenomics.ca>, Paul Stretenowich <paul.stretenowich@mcgill.ca>, Pierre-Olivier Quirion <po.quirion@mcgill.ca>, Edouard Henrion <edouard.henrion@computationalgenomics.ca>
Classifier: Programming Language :: Python :: 3
Classifier: License :: OSI Approved :: GNU Lesser General Public License v3 or later (LGPLv3+)
Classifier: Operating System :: POSIX
Classifier: Operating System :: Unix
Classifier: Operating System :: MacOS
Classifier: Intended Audience :: Science/Research
Classifier: Topic :: Scientific/Engineering :: Bio-Informatics
Project-URL: Homepage, https://github.com/c3g/GenPipes
Project-URL: Issues, https://github.com/c3g/GenPipes/issues
Project-URL: Documentation, https://genpipes.readthedocs.io
Requires-Python: >=3.12
Requires-Dist: packaging>=20.9
Requires-Dist: shtab>=1.7.1
Requires-Dist: questionary>=2.1.0
Requires-Dist: jinja2>=3.1.0
